<?xml version="1.0" encoding="UTF-8"?>
<response>

<lst name="responseHeader">
  <int name="status">0</int>
  <int name="QTime">20</int>
  <lst name="params">
    <str name="echoParams">explicit</str>
    <str name="indent">true</str>
    <str name="file">data-lines/./reut2-015.sgm-469.txt</str>
    <str name="usePOS">false</str>
    <str name="sentences">3</str>
    <str name="wt">xml</str>
    <str name="formula">tfidf</str>
  </lst>
</lst>
<lst name="analysis">
  <lst name="summary">
    <lst name="stats">
      <lst name="sentences">
        <int name="count">31</int>
      </lst>
      <lst name="terms">
        <int name="count">244</int>
      </lst>
      <lst name="stems">
        <int name="count">152</int>
      </lst>
    </lst>
    <lst name="terms">
      <lst name="term">
        <str name="text">balances</str>
        <double name="strength">1.0</double>
      </lst>
      <lst name="term">
        <str name="text">against</str>
        <double name="strength">0.9999999999999982</double>
      </lst>
      <lst name="term">
        <str name="text">acceptable</str>
        <double name="strength">0.999999999999997</double>
      </lst>
      <lst name="term">
        <str name="text">european</str>
        <double name="strength">0.5590169943749458</double>
      </lst>
      <lst name="term">
        <str name="text">strongly</str>
        <double name="strength">0.5000000000000003</double>
      </lst>
    </lst>
    <lst name="sentences">
      <lst name="sentence">
        <str name="text">The United States and France, backed by the International Monetary Fund, want the seven to agree on ranges or "norms" for a limited number of economic objectives such as growth, inflation, monetary conditions, trade balances and current account balances.</str>
        <int name="index">25</int>
        <int name="start">1</int>
        <int name="end">255</int>
        <double name="strength">1.0</double>
      </lst>
      <lst name="sentence">
        <str name="text">In a strongly worded statement terming the Japanese action "extraordinary and urgent", the meeting reaffirmed the Paris Accord by noting that current exchange rates are within ranges broadly consistent with fundamentals, or economic reality.</str>
        <int name="index">5</int>
        <int name="start">1</int>
        <int name="end">242</int>
        <double name="strength">0.925248865745601</double>
      </lst>
      <lst name="sentence">
        <str name="text">Bonn's finance minister Gerhard Stoltenberg argues that major currency shifts needed to remedy the huge imbalance between West Germany and Japan's trade surpluses and America's trade deficit have already taken place.</str>
        <int name="index">12</int>
        <int name="start">1</int>
        <int name="end">217</int>
        <double name="strength">0.9153766077358453</double>
      </lst>
    </lst>
    <lst name="highlighted">
      <lst name="sentence">
        <str name="text">The &lt;em&gt;United States&lt;/em&gt; and &lt;em&gt;France, backed&lt;/em&gt; by the &lt;em&gt;International Monetary&lt;/em&gt; Fund, want the &lt;em&gt;seven&lt;/em&gt; to &lt;em&gt;agree&lt;/em&gt; on &lt;em&gt;ranges&lt;/em&gt; or "&lt;em&gt;norms"&lt;/em&gt; for a &lt;em&gt;limited number&lt;/em&gt; of &lt;em&gt;economic objectives&lt;/em&gt; such as &lt;em&gt;growth, inflation, monetary conditions, trade balances&lt;/em&gt; and &lt;em&gt;current account balances&lt;/em&gt;.</str>
        <int name="index">25</int>
      </lst>
      <lst name="sentence">
        <str name="text">In a &lt;em&gt;strongly worded statement terming&lt;/em&gt; the &lt;em&gt;Japanese action "extraordinary&lt;/em&gt; and &lt;em&gt;urgent",&lt;/em&gt; the &lt;em&gt;meeting reaffirmed&lt;/em&gt; the &lt;em&gt;Paris Accord&lt;/em&gt; by &lt;em&gt;noting&lt;/em&gt; that &lt;em&gt;current exchange rates&lt;/em&gt; are &lt;em&gt;within ranges broadly consistent&lt;/em&gt; with &lt;em&gt;fundamentals,&lt;/em&gt; or &lt;em&gt;economic reality&lt;/em&gt;.</str>
        <int name="index">5</int>
      </lst>
      <lst name="sentence">
        <str name="text">Bonn's &lt;em&gt;finance minister Gerhard Stoltenberg argues&lt;/em&gt; that &lt;em&gt;major currency shifts needed&lt;/em&gt; to &lt;em&gt;remedy&lt;/em&gt; the huge &lt;em&gt;imbalance between&lt;/em&gt; West &lt;em&gt;Germany&lt;/em&gt; and &lt;em&gt;Japan&lt;/em&gt;'s &lt;em&gt;trade surpluses&lt;/em&gt; and &lt;em&gt;America&lt;/em&gt;'s &lt;em&gt;trade deficit&lt;/em&gt; have &lt;em&gt;already taken place&lt;/em&gt;.</str>
        <int name="index">12</int>
      </lst>
    </lst>
  </lst>
</lst>
</response>
