<?xml version="1.0" encoding="UTF-8"?>
<response>

<lst name="responseHeader">
  <int name="status">0</int>
  <int name="QTime">20</int>
  <lst name="params">
    <str name="echoParams">explicit</str>
    <str name="indent">true</str>
    <str name="file">data-lines/./reut2-017.sgm-293.txt</str>
    <str name="usePOS">false</str>
    <str name="sentences">3</str>
    <str name="wt">xml</str>
    <str name="formula">tfidf</str>
  </lst>
</lst>
<lst name="analysis">
  <lst name="summary">
    <lst name="stats">
      <lst name="sentences">
        <int name="count">34</int>
      </lst>
      <lst name="terms">
        <int name="count">213</int>
      </lst>
      <lst name="stems">
        <int name="count">134</int>
      </lst>
    </lst>
    <lst name="terms">
      <lst name="term">
        <str name="text">billion</str>
        <double name="strength">1.0</double>
      </lst>
      <lst name="term">
        <str name="text">probably</str>
        <double name="strength">0.5000000000000026</double>
      </lst>
      <lst name="term">
        <str name="text">often</str>
        <double name="strength">0.5000000000000018</double>
      </lst>
      <lst name="term">
        <str name="text">quotas</str>
        <double name="strength">0.5000000000000018</double>
      </lst>
      <lst name="term">
        <str name="text">perhaps</str>
        <double name="strength">0.5000000000000016</double>
      </lst>
    </lst>
    <lst name="sentences">
      <lst name="sentence">
        <str name="text">Although firming oil prices mean better news for Norway, Western Europe's biggest oil producer after Britain, analysts point to high interest rates, uncertainty over the future price of oil and a weighty current account balance of payments deficit as threats to the bourse.</str>
        <int name="index">21</int>
        <int name="start">1</int>
        <int name="end">274</int>
        <double name="strength">1.0</double>
      </lst>
      <lst name="sentence">
        <str name="text">The minority Labour government has looked increasingly stable since it came to power in May, 1986, with the former right-centrist coalition in disarray.</str>
        <int name="index">19</int>
        <int name="start">1</int>
        <int name="end">153</int>
        <double name="strength">0.9505295732416086</double>
      </lst>
      <lst name="sentence">
        <str name="text">But the attraction for foreign investors of the stock market, where price/earnings ratios average around a relatively low 11, is tempered by restrictions and some nervousness about the future of Norway's economy, analysts say.</str>
        <int name="index">8</int>
        <int name="start">1</int>
        <int name="end">227</int>
        <double name="strength">0.8876136370383261</double>
      </lst>
    </lst>
    <lst name="highlighted">
      <lst name="sentence">
        <str name="text">&lt;em&gt;Although firming&lt;/em&gt; oil &lt;em&gt;prices&lt;/em&gt; mean &lt;em&gt;better&lt;/em&gt; news for &lt;em&gt;Norway, Western Europe&lt;/em&gt;'s &lt;em&gt;biggest&lt;/em&gt; oil &lt;em&gt;producer after Britain, analysts point&lt;/em&gt; to high &lt;em&gt;interest rates, uncertainty&lt;/em&gt; over the &lt;em&gt;future price&lt;/em&gt; of oil and a &lt;em&gt;weighty current account balance&lt;/em&gt; of &lt;em&gt;payments deficit&lt;/em&gt; as &lt;em&gt;threats&lt;/em&gt; to the &lt;em&gt;bourse&lt;/em&gt;.</str>
        <int name="index">21</int>
      </lst>
      <lst name="sentence">
        <str name="text">The &lt;em&gt;minority Labour government&lt;/em&gt; has &lt;em&gt;looked increasingly stable since&lt;/em&gt; it came to &lt;em&gt;power&lt;/em&gt; in May, 1986, with the &lt;em&gt;former right-centrist coalition&lt;/em&gt; in &lt;em&gt;disarray&lt;/em&gt;.</str>
        <int name="index">19</int>
      </lst>
      <lst name="sentence">
        <str name="text">But the &lt;em&gt;attraction&lt;/em&gt; for &lt;em&gt;foreign investors&lt;/em&gt; of the &lt;em&gt;stock market, where price/earnings ratios average around&lt;/em&gt; a &lt;em&gt;relatively&lt;/em&gt; low 11, is &lt;em&gt;tempered&lt;/em&gt; by &lt;em&gt;restrictions&lt;/em&gt; and some &lt;em&gt;nervousness about&lt;/em&gt; the &lt;em&gt;future&lt;/em&gt; of &lt;em&gt;Norway&lt;/em&gt;'s &lt;em&gt;economy, analysts say&lt;/em&gt;.</str>
        <int name="index">8</int>
      </lst>
    </lst>
  </lst>
</lst>
</response>
