<?xml version="1.0" encoding="UTF-8"?>
<response>

<lst name="responseHeader">
  <int name="status">0</int>
  <int name="QTime">18</int>
  <lst name="params">
    <str name="echoParams">explicit</str>
    <str name="indent">true</str>
    <str name="file">data-lines/./reut2-009.sgm-109.txt</str>
    <str name="usePOS">false</str>
    <str name="sentences">3</str>
    <str name="wt">xml</str>
    <str name="formula">tfidf</str>
  </lst>
</lst>
<lst name="analysis">
  <lst name="summary">
    <lst name="stats">
      <lst name="sentences">
        <int name="count">34</int>
      </lst>
      <lst name="terms">
        <int name="count">146</int>
      </lst>
      <lst name="stems">
        <int name="count">92</int>
      </lst>
    </lst>
    <lst name="terms">
      <lst name="term">
        <str name="text">arvid</str>
        <double name="strength">1.0</double>
      </lst>
      <lst name="term">
        <str name="text">chevrolet</str>
        <double name="strength">0.5590169943749462</double>
      </lst>
      <lst name="term">
        <str name="text">power</str>
        <double name="strength">0.5000000000000017</double>
      </lst>
      <lst name="term">
        <str name="text">california</str>
        <double name="strength">0.5000000000000017</double>
      </lst>
      <lst name="term">
        <str name="text">based</str>
        <double name="strength">0.5000000000000017</double>
      </lst>
    </lst>
    <lst name="sentences">
      <lst name="sentence">
        <str name="text">The "Bug" caused "a rebellion" among dealers, who demanded greater freedom from restrictions placed on them by the major American automakers, says Jauppi.</str>
        <int name="index">9</int>
        <int name="start">0</int>
        <int name="end">154</int>
        <double name="strength">1.0</double>
      </lst>
      <lst name="sentence">
        <str name="text">There's not much that's off the table in terms of creative thinking" about ways to sell cars, says David Cole, analyst with the University of Michigan's Transportation Research Institute.</str>
        <int name="index">3</int>
        <int name="start">0</int>
        <int name="end">187</int>
        <double name="strength">0.9199215581898256</double>
      </lst>
      <lst name="sentence">
        <str name="text">D. Power, a California-based market research firm, says that, by 1990, 12,000 people will own dealerships compared to 16,800 principal owners today.</str>
        <int name="index">16</int>
        <int name="start">0</int>
        <int name="end">148</int>
        <double name="strength">0.9025970801447379</double>
      </lst>
    </lst>
    <lst name="highlighted">
      <lst name="sentence">
        <str name="text">The "Bug" &lt;em&gt;caused &lt;/em&gt;"a &lt;em&gt;rebellion" among dealers,&lt;/em&gt; who &lt;em&gt;demanded greater freedom&lt;/em&gt; from &lt;em&gt;restrictions placed&lt;/em&gt; on them by the &lt;em&gt;major American automakers,&lt;/em&gt; says &lt;em&gt;Jauppi&lt;/em&gt;.</str>
        <int name="index">9</int>
      </lst>
      <lst name="sentence">
        <str name="text">&lt;em&gt;There&lt;/em&gt;'s not much that's off the &lt;em&gt;table&lt;/em&gt; in &lt;em&gt;terms&lt;/em&gt; of &lt;em&gt;creative thinking" about&lt;/em&gt; ways to sell cars, says &lt;em&gt;David&lt;/em&gt; Cole, &lt;em&gt;analyst&lt;/em&gt; with the &lt;em&gt;University&lt;/em&gt; of &lt;em&gt;Michigan&lt;/em&gt;'s &lt;em&gt;Transportation Research Institute&lt;/em&gt;.</str>
        <int name="index">3</int>
      </lst>
      <lst name="sentence">
        <str name="text">D. &lt;em&gt;Power,&lt;/em&gt; a &lt;em&gt;California-based market research&lt;/em&gt; firm, says that, by 1990, 12,000 &lt;em&gt;people&lt;/em&gt; will own &lt;em&gt;dealerships compared&lt;/em&gt; to 16,800 &lt;em&gt;principal owners today&lt;/em&gt;.</str>
        <int name="index">16</int>
      </lst>
    </lst>
  </lst>
</lst>
</response>
