<?xml version="1.0" encoding="UTF-8"?>
<response>

<lst name="responseHeader">
  <int name="status">0</int>
  <int name="QTime">19</int>
  <lst name="params">
    <str name="echoParams">explicit</str>
    <str name="indent">true</str>
    <str name="file">data-lines/./reut2-002.sgm-774.txt</str>
    <str name="usePOS">false</str>
    <str name="sentences">3</str>
    <str name="wt">xml</str>
    <str name="formula">tfidf</str>
  </lst>
</lst>
<lst name="analysis">
  <lst name="summary">
    <lst name="stats">
      <lst name="sentences">
        <int name="count">29</int>
      </lst>
      <lst name="terms">
        <int name="count">181</int>
      </lst>
      <lst name="stems">
        <int name="count">111</int>
      </lst>
    </lst>
    <lst name="terms">
      <lst name="term">
        <str name="text">assumption</str>
        <double name="strength">1.0</double>
      </lst>
      <lst name="term">
        <str name="text">government</str>
        <double name="strength">0.999999999999998</double>
      </lst>
      <lst name="term">
        <str name="text">saudis</str>
        <double name="strength">0.559016994374947</double>
      </lst>
      <lst name="term">
        <str name="text">added</str>
        <double name="strength">0.5590169943749462</double>
      </lst>
      <lst name="term">
        <str name="text">tight</str>
        <double name="strength">0.5000000000000011</double>
      </lst>
    </lst>
    <lst name="sentences">
      <lst name="sentence">
        <str name="text">Stephen Hanke, chief economist at Friedburg Commodity Management, said OPEC production was lower "because of the Saudi cut (to 3.1 mln bpd) and this could spell trouble if it gives other members an incentive to exceed their quotas."</str>
        <int name="index">20</int>
        <int name="start">1</int>
        <int name="end">233</int>
        <double name="strength">1.0</double>
      </lst>
      <lst name="sentence">
        <str name="text">"OPEC is keeping its production down, and in the cash market there is tight supply of crude with short transportation time to major refining centers," said Daniel McKinley, oil analyst with Smith Barney, Harris Upham and Co. "</str>
        <int name="index">1</int>
        <int name="start">1</int>
        <int name="end">227</int>
        <double name="strength">0.8768722166420657</double>
      </lst>
      <lst name="sentence">
        <str name="text">"Oil traders were pulling prices down on the assumption that oil stocks were building and OPEC was producing well above its 15.8 mln bpd quota, but now both of those assumptions have come under question," McKinley said.</str>
        <int name="index">6</int>
        <int name="start">1</int>
        <int name="end">220</int>
        <double name="strength">0.8513980210870651</double>
      </lst>
    </lst>
    <lst name="highlighted">
      <lst name="sentence">
        <str name="text">&lt;em&gt;Stephen Hanke, chief economist&lt;/em&gt; at &lt;em&gt;Friedburg Commodity Management,&lt;/em&gt; said OPEC &lt;em&gt;production&lt;/em&gt; was &lt;em&gt;lower "because&lt;/em&gt; of the &lt;em&gt;Saudi&lt;/em&gt; cut (to 3.1 mln bpd) and this &lt;em&gt;could spell trouble&lt;/em&gt; if it &lt;em&gt;gives other members&lt;/em&gt; an &lt;em&gt;incentive&lt;/em&gt; to &lt;em&gt;exceed their quotas.&lt;/em&gt;"</str>
        <int name="index">20</int>
      </lst>
      <lst name="sentence">
        <str name="text">"OPEC is &lt;em&gt;keeping&lt;/em&gt; its &lt;em&gt;production&lt;/em&gt; down, and in the cash &lt;em&gt;market there&lt;/em&gt; is &lt;em&gt;tight supply&lt;/em&gt; of &lt;em&gt;crude&lt;/em&gt; with &lt;em&gt;short transportation&lt;/em&gt; time to &lt;em&gt;major refining centers,"&lt;/em&gt; said &lt;em&gt;Daniel McKinley,&lt;/em&gt; oil &lt;em&gt;analyst&lt;/em&gt; with &lt;em&gt;Smith Barney, Harris Upham&lt;/em&gt; and Co. "</str>
        <int name="index">1</int>
      </lst>
      <lst name="sentence">
        <str name="text">"Oil &lt;em&gt;traders&lt;/em&gt; were &lt;em&gt;pulling prices&lt;/em&gt; down on the &lt;em&gt;assumption&lt;/em&gt; that oil &lt;em&gt;stocks&lt;/em&gt; were &lt;em&gt;building&lt;/em&gt; and OPEC was &lt;em&gt;producing&lt;/em&gt; well &lt;em&gt;above&lt;/em&gt; its 15.8 mln bpd &lt;em&gt;quota,&lt;/em&gt; but now both of &lt;em&gt;those assumptions&lt;/em&gt; have come &lt;em&gt;under question," McKinley said&lt;/em&gt;.</str>
        <int name="index">6</int>
      </lst>
    </lst>
  </lst>
</lst>
</response>
