<?xml version="1.0" encoding="UTF-8"?>
<response>

<lst name="responseHeader">
  <int name="status">0</int>
  <int name="QTime">17</int>
  <lst name="params">
    <str name="echoParams">explicit</str>
    <str name="indent">true</str>
    <str name="file">data-lines/./reut2-011.sgm-731.txt</str>
    <str name="usePOS">false</str>
    <str name="sentences">3</str>
    <str name="wt">xml</str>
    <str name="formula">tfidf</str>
  </lst>
</lst>
<lst name="analysis">
  <lst name="summary">
    <lst name="stats">
      <lst name="sentences">
        <int name="count">28</int>
      </lst>
      <lst name="terms">
        <int name="count">149</int>
      </lst>
      <lst name="stems">
        <int name="count">82</int>
      </lst>
    </lst>
    <lst name="terms">
      <lst name="term">
        <str name="text">trade</str>
        <double name="strength">1.0</double>
      </lst>
      <lst name="term">
        <str name="text">their</str>
        <double name="strength">0.9999999999999998</double>
      </lst>
      <lst name="term">
        <str name="text">meetings</str>
        <double name="strength">0.9999999999999984</double>
      </lst>
      <lst name="term">
        <str name="text">american</str>
        <double name="strength">0.999999999999998</double>
      </lst>
      <lst name="term">
        <str name="text">maintain</str>
        <double name="strength">0.8944271909999172</double>
      </lst>
    </lst>
    <lst name="sentences">
      <lst name="sentence">
        <str name="text">Washington has extracted promises from both West Germany and Japan that they will take measures to bolster their domestic economic growth, to help reduce the massive gap between their huge trade surpluses and the record American trade deficit.</str>
        <int name="index">8</int>
        <int name="start">1</int>
        <int name="end">244</int>
        <double name="strength">1.0</double>
      </lst>
      <lst name="sentence">
        <str name="text">Western officials maintain the industrial world needs to expand at least three per cent annually -- against this year's initial IMF prediction of 2.5 pct -- in order to support the export drive of debtor nations.</str>
        <int name="index">18</int>
        <int name="start">0</int>
        <int name="end">212</int>
        <double name="strength">0.8664493590196722</double>
      </lst>
      <lst name="sentence">
        <str name="text">In recent days, the dollar has come under heavy selling pressure as markets have grown cynical that Bonn and Tokyo will take early action.</str>
        <int name="index">11</int>
        <int name="start">1</int>
        <int name="end">139</int>
        <double name="strength">0.8645376365279898</double>
      </lst>
    </lst>
    <lst name="highlighted">
      <lst name="sentence">
        <str name="text">&lt;em&gt;Washington&lt;/em&gt; has &lt;em&gt;extracted promises&lt;/em&gt; from both West &lt;em&gt;Germany&lt;/em&gt; and &lt;em&gt;Japan&lt;/em&gt; that they will take &lt;em&gt;measures&lt;/em&gt; to &lt;em&gt;bolster their domestic economic growth,&lt;/em&gt; to help &lt;em&gt;reduce&lt;/em&gt; the &lt;em&gt;massive&lt;/em&gt; gap &lt;em&gt;between their&lt;/em&gt; huge &lt;em&gt;trade surpluses&lt;/em&gt; and the &lt;em&gt;record American trade deficit&lt;/em&gt;.</str>
        <int name="index">8</int>
      </lst>
      <lst name="sentence">
        <str name="text">&lt;em&gt;Western officials maintain&lt;/em&gt; the &lt;em&gt;industrial world needs&lt;/em&gt; to &lt;em&gt;expand&lt;/em&gt; at &lt;em&gt;least three&lt;/em&gt; per cent &lt;em&gt;annually -- against&lt;/em&gt; this year's &lt;em&gt;initial&lt;/em&gt; IMF &lt;em&gt;prediction&lt;/em&gt; of 2.5 pct -- in &lt;em&gt;order&lt;/em&gt; to &lt;em&gt;support&lt;/em&gt; the &lt;em&gt;export drive&lt;/em&gt; of &lt;em&gt;debtor nations&lt;/em&gt;.</str>
        <int name="index">18</int>
      </lst>
      <lst name="sentence">
        <str name="text">In &lt;em&gt;recent&lt;/em&gt; days, the &lt;em&gt;dollar&lt;/em&gt; has come &lt;em&gt;under heavy selling pressure&lt;/em&gt; as &lt;em&gt;markets&lt;/em&gt; have &lt;em&gt;grown cynical&lt;/em&gt; that Bonn and &lt;em&gt;Tokyo&lt;/em&gt; will take &lt;em&gt;early action&lt;/em&gt;.</str>
        <int name="index">11</int>
      </lst>
    </lst>
  </lst>
</lst>
</response>
