<?xml version="1.0" encoding="UTF-8"?>
<response>

<lst name="responseHeader">
  <int name="status">0</int>
  <int name="QTime">21</int>
  <lst name="params">
    <str name="echoParams">explicit</str>
    <str name="indent">true</str>
    <str name="file">data-lines/./reut2-005.sgm-630.txt</str>
    <str name="usePOS">false</str>
    <str name="sentences">3</str>
    <str name="wt">xml</str>
    <str name="formula">tfidf</str>
  </lst>
</lst>
<lst name="analysis">
  <lst name="summary">
    <lst name="stats">
      <lst name="sentences">
        <int name="count">36</int>
      </lst>
      <lst name="terms">
        <int name="count">221</int>
      </lst>
      <lst name="stems">
        <int name="count">142</int>
      </lst>
    </lst>
    <lst name="terms">
      <lst name="term">
        <str name="text">another</str>
        <double name="strength">1.0</double>
      </lst>
      <lst name="term">
        <str name="text">negative</str>
        <double name="strength">1.0</double>
      </lst>
      <lst name="term">
        <str name="text">hostile</str>
        <double name="strength">1.0</double>
      </lst>
      <lst name="term">
        <str name="text">takeovers</str>
        <double name="strength">1.0</double>
      </lst>
      <lst name="term">
        <str name="text">leveraged</str>
        <double name="strength">1.0</double>
      </lst>
    </lst>
    <lst name="sentences">
      <lst name="sentence">
        <str name="text">In bond portfolios, the money managers generally showed a preference for shorter term (10 years and under) Treasury notes and, to a lesser extent, agency securities, rather than longer-dated Treasury issues and corporate bonds.</str>
        <int name="index">31</int>
        <int name="start">1</int>
        <int name="end">228</int>
        <double name="strength">1.0</double>
      </lst>
      <lst name="sentence">
        <str name="text">"In the near term, the stock market has more prospects for growth, due to the mixed signals on the economy so far, the slim chance the Federal Reserve will ease policy and still heavy debt accumulation," Collins said.</str>
        <int name="index">24</int>
        <int name="start">1</int>
        <int name="end">218</int>
        <double name="strength">0.9797737708267847</double>
      </lst>
      <lst name="sentence">
        <str name="text">Lisec-Tinto, who formulated Merrill's latest asset mix recommendations with new chief investment strategist Charles Clough, said there may be some consolidation of recent stock price gains, but the market appears to have good potential.</str>
        <int name="index">3</int>
        <int name="start">1</int>
        <int name="end">237</int>
        <double name="strength">0.9756618447728884</double>
      </lst>
    </lst>
    <lst name="highlighted">
      <lst name="sentence">
        <str name="text">In bond &lt;em&gt;portfolios,&lt;/em&gt; the &lt;em&gt;money managers generally showed&lt;/em&gt; a &lt;em&gt;preference&lt;/em&gt; for &lt;em&gt;shorter&lt;/em&gt; term (10 &lt;em&gt;years&lt;/em&gt; and &lt;em&gt;under) Treasury notes&lt;/em&gt; and, to a &lt;em&gt;lesser extent, agency securities, rather&lt;/em&gt; than &lt;em&gt;longer-dated Treasury issues&lt;/em&gt; and &lt;em&gt;corporate bonds&lt;/em&gt;.</str>
        <int name="index">31</int>
      </lst>
      <lst name="sentence">
        <str name="text">"In the near term, the &lt;em&gt;stock market&lt;/em&gt; has more &lt;em&gt;prospects&lt;/em&gt; for &lt;em&gt;growth,&lt;/em&gt; due to the &lt;em&gt;mixed signals&lt;/em&gt; on the &lt;em&gt;economy&lt;/em&gt; so far, the slim &lt;em&gt;chance&lt;/em&gt; the &lt;em&gt;Federal Reserve&lt;/em&gt; will ease &lt;em&gt;policy&lt;/em&gt; and &lt;em&gt;still heavy&lt;/em&gt; debt &lt;em&gt;accumulation," Collins said&lt;/em&gt;.</str>
        <int name="index">24</int>
      </lst>
      <lst name="sentence">
        <str name="text">&lt;em&gt;Lisec-Tinto,&lt;/em&gt; who &lt;em&gt;formulated Merrill&lt;/em&gt;'s &lt;em&gt;latest asset&lt;/em&gt; mix &lt;em&gt;recommendations&lt;/em&gt; with new &lt;em&gt;chief investment strategist Charles Clough,&lt;/em&gt; said &lt;em&gt;there&lt;/em&gt; may be some &lt;em&gt;consolidation&lt;/em&gt; of &lt;em&gt;recent stock price gains,&lt;/em&gt; but the &lt;em&gt;market appears&lt;/em&gt; to have good &lt;em&gt;potential&lt;/em&gt;.</str>
        <int name="index">3</int>
      </lst>
    </lst>
  </lst>
</lst>
</response>
