<?xml version="1.0" encoding="UTF-8"?>
<response>

<lst name="responseHeader">
  <int name="status">0</int>
  <int name="QTime">18</int>
  <lst name="params">
    <str name="echoParams">explicit</str>
    <str name="indent">true</str>
    <str name="file">data-lines/./reut2-009.sgm-773.txt</str>
    <str name="usePOS">false</str>
    <str name="sentences">3</str>
    <str name="wt">xml</str>
    <str name="formula">tfidf</str>
  </lst>
</lst>
<lst name="analysis">
  <lst name="summary">
    <lst name="stats">
      <lst name="sentences">
        <int name="count">25</int>
      </lst>
      <lst name="terms">
        <int name="count">179</int>
      </lst>
      <lst name="stems">
        <int name="count">121</int>
      </lst>
    </lst>
    <lst name="terms">
      <lst name="term">
        <str name="text">party</str>
        <double name="strength">1.0</double>
      </lst>
      <lst name="term">
        <str name="text">centre</str>
        <double name="strength">0.8944271909999181</double>
      </lst>
      <lst name="term">
        <str name="text">running</str>
        <double name="strength">0.8944271909999181</double>
      </lst>
      <lst name="term">
        <str name="text">discussions</str>
        <double name="strength">0.8944271909999181</double>
      </lst>
      <lst name="term">
        <str name="text">renewal</str>
        <double name="strength">0.8944271909999181</double>
      </lst>
    </lst>
    <lst name="sentences">
      <lst name="sentence">
        <str name="text">The "laundering" of drug and "insider dealing" money and controversy over accounts of the ousted Philippine and Haitian Presidents have hurt the standing of Swiss banks recently and strained international relations, particularly with the United States.</str>
        <int name="index">1</int>
        <int name="start">1</int>
        <int name="end">253</int>
        <double name="strength">1.0</double>
      </lst>
      <lst name="sentence">
        <str name="text">The role of lawyers has been at the centre of long running discussions on the renewal of the so-called "convention of diligence," a voluntary code of banking conduct introduced in response to a major banking scandal here in 1977.</str>
        <int name="index">8</int>
        <int name="start">1</int>
        <int name="end">230</int>
        <double name="strength">0.8990449263838487</double>
      </lst>
      <lst name="sentence">
        <str name="text">With secrecy back in the public eye due to the Ferdinand Marcos case and a Swiss bank link to the recently busted "Pizza Connection" international heroin ring, officials at the Banking Commission said earlier this year they wanted a tightening of rules on anonymity.</str>
        <int name="index">9</int>
        <int name="start">1</int>
        <int name="end">267</int>
        <double name="strength">0.8564087329632342</double>
      </lst>
    </lst>
    <lst name="highlighted">
      <lst name="sentence">
        <str name="text">The "&lt;em&gt;laundering"&lt;/em&gt; of drug and "&lt;em&gt;insider dealing" money&lt;/em&gt; and &lt;em&gt;controversy&lt;/em&gt; over &lt;em&gt;accounts&lt;/em&gt; of the &lt;em&gt;ousted Philippine&lt;/em&gt; and &lt;em&gt;Haitian Presidents&lt;/em&gt; have hurt the &lt;em&gt;standing&lt;/em&gt; of &lt;em&gt;Swiss banks recently&lt;/em&gt; and &lt;em&gt;strained international relations, particularly&lt;/em&gt; with the &lt;em&gt;United States&lt;/em&gt;.</str>
        <int name="index">1</int>
      </lst>
      <lst name="sentence">
        <str name="text">The role of &lt;em&gt;lawyers&lt;/em&gt; has been at the &lt;em&gt;centre&lt;/em&gt; of long &lt;em&gt;running discussions&lt;/em&gt; on the &lt;em&gt;renewal&lt;/em&gt; of the so-&lt;em&gt;called "convention&lt;/em&gt; of &lt;em&gt;diligence,"&lt;/em&gt; a &lt;em&gt;voluntary&lt;/em&gt; code of &lt;em&gt;banking conduct introduced&lt;/em&gt; in &lt;em&gt;response&lt;/em&gt; to a &lt;em&gt;major banking scandal&lt;/em&gt; here in 1977.</str>
        <int name="index">8</int>
      </lst>
      <lst name="sentence">
        <str name="text">With &lt;em&gt;secrecy&lt;/em&gt; back in the &lt;em&gt;public&lt;/em&gt; eye due to the &lt;em&gt;Ferdinand Marcos&lt;/em&gt; case and a &lt;em&gt;Swiss&lt;/em&gt; bank link to the &lt;em&gt;recently busted "Pizza Connection" international heroin&lt;/em&gt; ring, &lt;em&gt;officials&lt;/em&gt; at the &lt;em&gt;Banking Commission&lt;/em&gt; said &lt;em&gt;earlier&lt;/em&gt; this year they &lt;em&gt;wanted&lt;/em&gt; a &lt;em&gt;tightening&lt;/em&gt; of &lt;em&gt;rules&lt;/em&gt; on &lt;em&gt;anonymity&lt;/em&gt;.</str>
        <int name="index">9</int>
      </lst>
    </lst>
  </lst>
</lst>
</response>
